benchmark/__init__.py
benchmark/benchmark.py
benchmark/test_benchmark.py
benchmark/xmls/arm.xml
benchmark/xmls/gait.xml
imt_benchmark-0.0.2.dist-info/METADATA
imt_benchmark-0.0.2.dist-info/WHEEL
imt_benchmark-0.0.2.dist-info/top_level.txt
imt_benchmark-0.0.2.dist-info/RECORD
